testingfq/Aggregates.py
testingfq/Aggregates.pyi
testingfq/CoveredWarrantData.py
testingfq/CoveredWarrantData.pyi
testingfq/DerivativeData.py
testingfq/DerivativeData.pyi
testingfq/FiinIndicator.py
testingfq/FiinIndicator.pyi
testingfq/FiinSession.py
testingfq/FiinSession.pyi
testingfq/IndexData.py
testingfq/IndexData.pyi
testingfq/SubscribeCoveredWarrantEvents.py
testingfq/SubscribeCoveredWarrantEvents.pyi
testingfq/SubscribeDerivativeEvents.py
testingfq/SubscribeDerivativeEvents.pyi
testingfq/SubscribeIndexEvents.py
testingfq/SubscribeIndexEvents.pyi
testingfq/SubscribeTickerEvents.py
testingfq/SubscribeTickerEvents.pyi
testingfq/SubscribeTickerUpdate.py
testingfq/SubscribeTickerUpdate.pyi
testingfq/TickerData.py
testingfq/TickerData.pyi
testingfq/__init__.py
testingfq-0.0.0.10.dist-info/METADATA
testingfq-0.0.0.10.dist-info/WHEEL
testingfq-0.0.0.10.dist-info/top_level.txt
testingfq-0.0.0.10.dist-info/RECORD
